newbringer_picamera2-0.3.30.dist-info/licenses/LICENSE
picamera2/__init__.py
picamera2/configuration.py
picamera2/controls.py
picamera2/converters.py
picamera2/dma_heap.py
picamera2/formats.py
picamera2/job.py
picamera2/metadata.py
picamera2/picamera2.py
picamera2/platform.py
picamera2/request.py
picamera2/sensor_format.py
picamera2/utils.py
picamera2/allocators/__init__.py
picamera2/allocators/allocator.py
picamera2/allocators/dmaallocator.py
picamera2/allocators/libcameraallocator.py
picamera2/allocators/persistent_allocator.py
picamera2/devices/__init__.py
picamera2/devices/hailo/__init__.py
picamera2/devices/hailo/hailo.py
picamera2/devices/imx500/__init__.py
picamera2/devices/imx500/imx500.py
picamera2/devices/imx500/postprocess.py
picamera2/devices/imx500/postprocess_efficientdet_lite0.py
picamera2/devices/imx500/postprocess_highernet.py
picamera2/devices/imx500/postprocess_nanodet.py
picamera2/devices/imx500/postprocess_yolov5.py
picamera2/devices/imx500/postprocess_yolov8.py
picamera2/devices/imx708/__init__.py
picamera2/devices/imx708/imx708.py
picamera2/encoders/__init__.py
picamera2/encoders/encoder.py
picamera2/encoders/h264_encoder.py
picamera2/encoders/jpeg_encoder.py
picamera2/encoders/libav_h264_encoder.py
picamera2/encoders/libav_mjpeg_encoder.py
picamera2/encoders/mjpeg_encoder.py
picamera2/encoders/multi_encoder.py
picamera2/encoders/v4l2_encoder.py
picamera2/outputs/__init__.py
picamera2/outputs/circularoutput.py
picamera2/outputs/circularoutput2.py
picamera2/outputs/ffmpegoutput.py
picamera2/outputs/fileoutput.py
picamera2/outputs/output.py
picamera2/outputs/pyavoutput.py
picamera2/outputs/splittableoutput.py
picamera2/previews/__init__.py
picamera2/previews/drm_preview.py
picamera2/previews/gl_helpers.py
picamera2/previews/null_preview.py
picamera2/previews/q_gl_picamera2.py
picamera2/previews/q_picamera2.py
picamera2/previews/qt.py
picamera2/previews/qt_compatibility.py
picamera2/previews/qt_previews.py
newbringer_picamera2-0.3.30.dist-info/METADATA
newbringer_picamera2-0.3.30.dist-info/WHEEL
newbringer_picamera2-0.3.30.dist-info/top_level.txt
newbringer_picamera2-0.3.30.dist-info/RECORD
