Metadata-Version: 2.4
Name: newbringer-picamera2
Version: 0.3.30
Summary: The libcamera-based Python interface to Raspberry Pi cameras, based on the original Picamera library
Home-page: https://github.com/RaspberryPi/picamera2
Author: Raspberry Pi & Raspberry Pi Foundation
Author-email: picamera2@raspberrypi.com
License: BSD 2-Clause License
Project-URL: Bug Tracker, https://github.com/RaspberryPi/picamera2/issues
Classifier: Development Status :: 4 - Beta
Classifier: Intended Audience :: Developers
Classifier: License :: OSI Approved :: BSD License
Classifier: Operating System :: POSIX :: Linux
Classifier: Programming Language :: Python :: 3.9
Classifier: Topic :: Multimedia :: Graphics :: Capture :: Digital Camera
Requires-Python: >=3.9
License-File: LICENSE
Requires-Dist: numpy
Requires-Dist: PiDNG
Requires-Dist: piexif
Requires-Dist: pillow
Requires-Dist: simplejpeg
Requires-Dist: videodev2
Requires-Dist: python-prctl
Requires-Dist: av
Requires-Dist: libarchive-c
Requires-Dist: tqdm
Requires-Dist: jsonschema
Provides-Extra: gui
Requires-Dist: pyopengl; extra == "gui"
Requires-Dist: PyQt5; extra == "gui"
Dynamic: author
Dynamic: author-email
Dynamic: classifier
Dynamic: description
Dynamic: description-content-type
Dynamic: home-page
Dynamic: license
Dynamic: license-file
Dynamic: project-url
Dynamic: provides-extra
Dynamic: requires-dist
Dynamic: requires-python
Dynamic: summary
